fco/LICENSE
fco/README.MD
fco/__init__.py
fco/requirements.txt
fco/thirdparty.json
fco-0.10.dist-info/LICENSE.rst
fco-0.10.dist-info/METADATA
fco-0.10.dist-info/WHEEL
fco-0.10.dist-info/top_level.txt
fco-0.10.dist-info/RECORD
